donuts/__init__.py
donuts/array.py
donuts/jvm.py
donuts/poly.py
donuts/py.typed
donuts/rat.py
donuts/var.py
donuts/varset.py
donuts/java/donuts-all.jar
donuts_python-0.0.5.dist-info/LICENSE
donuts_python-0.0.5.dist-info/METADATA
donuts_python-0.0.5.dist-info/WHEEL
donuts_python-0.0.5.dist-info/top_level.txt
donuts_python-0.0.5.dist-info/RECORD
