Metadata-Version: 2.1
Name: donuts-python
Version: 0.0.5
Summary: Python binding to Donuts
Home-page: https://github.com/tueda/donuts-python
Author: Takahiro Ueda
Author-email: t.ueda.od@juntendo.ac.jp
License: MIT
Keywords: computer algebra,multivariate polynomial arithmetic
Classifier: Development Status :: 2 - Pre-Alpha
Classifier: Intended Audience :: Science/Research
Classifier: License :: OSI Approved :: MIT License
Classifier: Programming Language :: Python :: 3.7
Classifier: Programming Language :: Python :: 3.8
Classifier: Programming Language :: Python :: 3.9
Classifier: Programming Language :: Python :: 3.10
Classifier: Programming Language :: Python :: 3.11
Classifier: Programming Language :: Python :: 3.12
Classifier: Topic :: Scientific/Engineering :: Mathematics
Requires-Python: >=3.7
License-File: LICENSE
Requires-Dist: pyjnius
Requires-Dist: importlib-resources >=1.3 ; python_version < "3.9"
